pygloo.so
pygloo_rec-0.2.0.dist-info/LICENSE
pygloo_rec-0.2.0.dist-info/METADATA
pygloo_rec-0.2.0.dist-info/WHEEL
pygloo_rec-0.2.0.dist-info/top_level.txt
pygloo_rec-0.2.0.dist-info/RECORD
